evo_spotis/__init__.py
evo_spotis/additions.py
evo_spotis/correlations.py
evo_spotis/normalizations.py
evo_spotis/weighting_methods.py
evo_spotis/mcda_methods/__init__.py
evo_spotis/mcda_methods/mcda_method.py
evo_spotis/mcda_methods/spotis.py
evo_spotis/stochastic_algorithms/__init__.py
evo_spotis/stochastic_algorithms/de.py
evo_spotis-0.0.9.dist-info/LICENSE
evo_spotis-0.0.9.dist-info/METADATA
evo_spotis-0.0.9.dist-info/WHEEL
evo_spotis-0.0.9.dist-info/top_level.txt
evo_spotis-0.0.9.dist-info/RECORD
