Metadata-Version: 2.1
Name: evo-spotis
Version: 0.0.9
Summary: Package for Multi-Criteria Decision Analysis with Preference Identification
Home-page: https://github.com/energyinpython/EVO-SPOTIS
Author: Aleksandra Ba
Author-email: aleksandra.baczkiewicz@phd.usz.edu.pl
License: UNKNOWN
Platform: UNKNOWN
Classifier: Programming Language :: Python :: 3
Classifier: License :: OSI Approved :: MIT License
Classifier: Operating System :: OS Independent
Requires-Python: >=3.4
License-File: LICENSE
Requires-Dist: numpy
